tests/__init__.py
tests/test_main.py
totalpwd/__init__.py
totalpwd/__main__.py
totalpwd/__version__.py
TotalPwd-0.0.1.dist-info/LICENSE
TotalPwd-0.0.1.dist-info/METADATA
TotalPwd-0.0.1.dist-info/WHEEL
TotalPwd-0.0.1.dist-info/entry_points.txt
TotalPwd-0.0.1.dist-info/top_level.txt
TotalPwd-0.0.1.dist-info/RECORD
